spire/__init__.py
spire/__main__.py
spire/ants.py
spire/misc.py
spire/task.py
spire/task_factory.py
spire/task_graph.py
spire/spm/__init__.py
spire/spm/contrast_manager.py
spire/spm/factorial_design.py
spire/spm/image_calculator.py
spire/spm/model_estimation.py
spire/spm/spm_object.py
spire/spm/stats.py
spire/spm/utils.py
spire_pipeline-1.2.1.dist-info/LICENSE.txt
spire_pipeline-1.2.1.dist-info/METADATA
spire_pipeline-1.2.1.dist-info/WHEEL
spire_pipeline-1.2.1.dist-info/top_level.txt
spire_pipeline-1.2.1.dist-info/RECORD
