Metadata-Version: 2.1
Name: spire-pipeline
Version: 1.2.1
Summary: Run software pipelines using doit
Home-page: https://github.com/lamyj/spire
Author: Julien Lamy
Author-email: lamy@unistra.fr
License: MIT
Keywords: pipeline,workflow,task execution
Platform: UNKNOWN
Classifier: Development Status :: 5 - Production/Stable
Classifier: Environment :: Console
Classifier: Intended Audience :: Developers
Classifier: Intended Audience :: Science/Research
Classifier: Topic :: Software Development :: Build Tools
Classifier: Topic :: Scientific/Engineering
Classifier: License :: OSI Approved :: MIT License
Classifier: Programming Language :: Python :: 3
Requires-Dist: doit
Requires-Dist: jinja2
Requires-Dist: numpy
